socket_handler/__init__.py
polog_socket_handler-0.0.1.dist-info/METADATA
polog_socket_handler-0.0.1.dist-info/WHEEL
polog_socket_handler-0.0.1.dist-info/top_level.txt
polog_socket_handler-0.0.1.dist-info/RECORD
