Metadata-Version: 2.1
Name: polog-socket-handler
Version: 0.0.1
Summary: Handler для polog
Home-page: https://github.com/Thereodorex/polog_handler_socket
Author: Fedor Malkov
Author-email: qwert199600@mail.ru
License: UNKNOWN
Platform: UNKNOWN
Classifier: Programming Language :: Python :: 3.8
Classifier: License :: OSI Approved :: MIT License
Requires-Dist: python-dateutil (==2.8.1)
